strict_fields/__init__.py
strict_fields/apps.py
strict_fields/fields.py
strict_fields/helpers.py
strict_fields/version.py
django_strict_fields-1.4.0.dist-info/LICENSE
django_strict_fields-1.4.0.dist-info/METADATA
django_strict_fields-1.4.0.dist-info/WHEEL
django_strict_fields-1.4.0.dist-info/RECORD
