Metadata-Version: 2.1
Name: django-strict-fields
Version: 1.4.0
Summary: A collection of fields and utilities to help make model fields more strict.
Home-page: https://github.com/Opus10/django-strict-fields
License: BSD-3-Clause
Author: Tomas Arni Jonasson
Requires-Python: >=3.9.0,<4
Classifier: Framework :: Django
Classifier: Framework :: Django :: 4.2
Classifier: Framework :: Django :: 5.0
Classifier: Framework :: Django :: 5.1
Classifier: Intended Audience :: Developers
Classifier: License :: OSI Approved :: BSD License
Classifier: Operating System :: OS Independent
Classifier: Programming Language :: Python
Classifier: Programming Language :: Python :: 3
Classifier: Programming Language :: Python :: 3.9
Classifier: Programming Language :: Python :: 3.10
Classifier: Programming Language :: Python :: 3.11
Classifier: Programming Language :: Python :: 3.12
Classifier: Programming Language :: Python :: 3.13
Classifier: Programming Language :: Python :: 3 :: Only
Requires-Dist: django (>=4)
Project-URL: Documentation, https://django-strict-fields.readthedocs.io
Project-URL: Repository, https://github.com/Opus10/django-strict-fields
